[
    {
        "id": 1,
        "img": "/images/others_01.jpg",
        "title": "Starbucks",
        "description": "API動作の実装で上記のアプリを作成",
        "link": "https://starbucks-app.vercel.app/",
        "sitedesc": "使用ツール及びフレームワーク",
        "tools": [
            "フレームワーク: Next.js",
            "プラットフォーム: Vercel",
            "APIテストツール: Postman",
            "Designツール: Adobe XD"
        ]
    },
    {
        "id": 2,
        "img": "/images/others_02.jpg",
        "title": "House Marketplace",
        "description": "AirbnbのようなWEBアプリを作成。ログインするとRent, Saleに出したい物件を掲載できます。",
        "link": "https://house-markectplace.vercel.app/",
        "sitedesc": "使用ツール及びフレームワーク",
        "tools": [
            "フレームワーク: React.js",
            "プラットフォーム: Vercel",
            "データベース: Google Firebase",
            "APIテストツール: Postman"
        ]
    },
    {
        "id": 3,
        "img": "/images/others_03.jpg",
        "title": "Support Desk App",
        "description": "サポートセンターを想定したアプリ。特徴は、Reactならではのページ移動、動作のレスポンスが早いこと。",
        "link": "https://shutosupprtdesk.herokuapp.com/",
        "sitedesc:": "使用ツール及びフレームワーク",
        "tools": [
            "フレームワーク: React.js",
            "プラットフォーム: Heroku",
            "データベース: MongoDB",
            "APIテストツール: Postman"
        ]
    }


]